app_store_scrapr/__init__.py
app_store_scrapr/reviews.py
app_store_scrapr/utils/__init__.py
app_store_scrapr/utils/requests.py
app_store_scrapr-0.1.0.dist-info/LICENSE
app_store_scrapr-0.1.0.dist-info/METADATA
app_store_scrapr-0.1.0.dist-info/WHEEL
app_store_scrapr-0.1.0.dist-info/RECORD
